tominjinja/__init__.py
tominjinja/__main__.py
tominjinja-0.2.0.dist-info/METADATA
tominjinja-0.2.0.dist-info/WHEEL
tominjinja-0.2.0.dist-info/RECORD
