Metadata-Version: 2.1
Name: tominjinja
Version: 0.2.0
Summary: 
Author: Marcin Tyszkiewicz
Author-email: 56219944+mtyszkiewicz@users.noreply.github.com
Requires-Python: >=3.9,<4.0
Classifier: Programming Language :: Python :: 3
Classifier: Programming Language :: Python :: 3.9
Classifier: Programming Language :: Python :: 3.10
Classifier: Programming Language :: Python :: 3.11
Requires-Dist: jinja2 (>=3.1.2,<4.0.0)
Requires-Dist: rich-argparse (>=1.3.0,<2.0.0)
Requires-Dist: toml (>=0.10.2,<0.11.0)
